1_activity/RTL/Encoder.v
module Encoder(
// Power nodes
inout vdd, // Supply
inout vss, // GND
// Inputs
input [6:0] Comp, // Comparators outputs
input Samp, // Sampling signal
input clk, // Clock
// Outputs
output reg [2:0] Dout, // Digital ADC output
output reg eoc // End of conversion
);

// >> Encoder:
// Next Out value
reg [2:0] Bx;
always @* begin
case (Comp)
7'b0000000: Bx = 3'b000;
7'b0000001: Bx = 3'b001;
7'b0000011: Bx = 3'b010;
7'b0000111: Bx = 3'b011;
7'b0001111: Bx = 3'b100;
7'b0011111: Bx = 3'b101;
7'b0111111: Bx = 3'b110;
7'b1111111: Bx = 3'b111;
default: Bx = 3'b000;
endcase
end

always @(posedge clk) begin
if (Samp == 1'b1) begin
Dout[2:0] <= 3'd0;
eoc <= 1'd0;
end else if(Samp == 1'b0) begin
Dout[2:0] <= Bx;
eoc <= 1'd1;
end
end

endmodule

1_activity/RTL/Encoder_TB.v
`timescale 1ns/10ps

module Encoder_tb;
// Inputs and outputs
reg [6:0] Comp_tb; // Comparators outputs
reg Samp_tb; // Sampling signal
reg clk_tb; // Clock
wire [2:0] Dout_tb; // Digital ADC output
wire eoc_tb; // End of conversion

// Instance of the Encoder module
Encoder uut (
.Comp(Comp_tb),
.Samp(Samp_tb),
.clk(clk_tb),
.Dout(Dout_tb),
.eoc(eoc_tb)
);

// Clock generation
initial clk_tb = 0;
always #5 clk_tb = ~ clk_tb; // Clock period = 10 ns

// Stimulus block
initial begin
    $dumpfile("Waveforms.vcd"); // VCD file for waveform visualization
    $dumpvars(0, Encoder_tb); // Dump all variables in the testbench

    // Test Comp_tb values
    #10 Samp_tb = 0; Comp_tb = 7'b0000000; // Dout => 3'b001
    #10 Samp_tb = 0; Comp_tb = 7'b0000001; // Dout => 3'b000
    #10 Samp_tb = 0; Comp_tb = 7'b0000011; // Dout => 3'b010
    #10 Samp_tb = 0; Comp_tb = 7'b0000111; // Dout => 3'b011
    #10 Samp_tb = 0; Comp_tb = 7'b0001111; // Dout => 3'b100
    #10 Samp_tb = 0; Comp_tb = 7'b0011111; // Dout => 3'b101
    #10 Samp_tb = 0; Comp_tb = 7'b0111111; // Dout => 3'b110
    #10 Samp_tb = 0; Comp_tb = 7'b1111111; // Dout => 3'b111
    // End simulation
    #10 $finish;
end

initial begin

    // Test Comp_tb values
    #10 Samp_tb = 0; Comp_tb = 7'b0000000; // Dout => 3'b001
    #10 Samp_tb = 0; Comp_tb = 7'b0000001; // Dout => 3'b000
    #10 Samp_tb = 0; Comp_tb = 7'b0000011; // Dout => 3'b010
    // End simulation
    #10 $finish;
end

// Monitor outputs
    initial begin
        $monitor("Time: %0t | Samp: %b | Comp: %b | Dout: %b | eoc: %b",
                $time, Samp_tb, Comp_tb, Dout_tb, eoc_tb);
    end

endmodule

1_activity/RTL/Waveforms.vcd
$date
	Thu Apr  9 00:27:44 2026
$end
$version
	Icarus Verilog
$end
$timescale
	10ps
$end
$scope module Encoder_tb $end
$var wire 1 ! eoc_tb $end
$var wire 3 " Dout_tb [2:0] $end
$var reg 7 # Comp_tb [6:0] $end
$var reg 1 $ Samp_tb $end
$var reg 1 % clk_tb $end
$scope module uut $end
$var wire 7 & Comp [6:0] $end
$var wire 1 $ Samp $end
$var wire 1 % clk $end
$var wire 1 ' vdd $end
$var wire 1 ( vss $end
$var reg 3 ) Bx [2:0] $end
$var reg 3 * Dout [2:0] $end
$var reg 1 ! eoc $end
$upscope $end
$upscope $end
$enddefinitions $end
$comment Show the parameter values. $end
$dumpall
$end
#0
$dumpvars
bx *
bx )
z(
z'
bx &
0%
x$
bx #
bx "
x!
$end
#500
1%
#1000
b0 )
0%
b0 #
b0 &
0$
#1500
1!
b0 "
b0 *
1%
#2000
b1 )
0%
b1 #
b1 &
0$
#2500
b1 "
b1 *
1%
#3000
b10 )
0%
b11 #
b11 &
0$
#3500
b10 "
b10 *
1%
#4000
b11 )
0%
b111 #
b111 &
